airflow_dbt/__init__.py
airflow_dbt/__version__.py
airflow_dbt/dbt_command_config.py
airflow_dbt/hooks/__init__.py
airflow_dbt/hooks/base.py
airflow_dbt/hooks/cli.py
airflow_dbt/hooks/google.py
airflow_dbt/operators/__init__.py
airflow_dbt/operators/dbt_operator.py
airflow_dbt/operators/google.py
airflow_dbt_dinigo-0.5.10.dist-info/METADATA
airflow_dbt_dinigo-0.5.10.dist-info/WHEEL
airflow_dbt_dinigo-0.5.10.dist-info/licenses/LICENSE.txt
airflow_dbt_dinigo-0.5.10.dist-info/RECORD
