Metadata-Version: 2.1
Name: airflow-dbt-dinigo
Version: 0.5.10
Summary: Apache Airflow integration for dbt
License-File: LICENSE.txt
Classifier: Development Status :: 5 - Production/Stable
Classifier: License :: OSI Approved :: MIT License
Classifier: Operating System :: MacOS :: MacOS X
Classifier: Operating System :: POSIX :: Linux
Classifier: Programming Language :: Python :: 3.7
Requires-Dist: apache-airflow>=1.10.3
Provides-Extra: google
Requires-Dist: apache-airflow-providers-google; extra == 'google'
Requires-Dist: google-cloud-build; extra == 'google'
